package1/__init__.py
package1/p1.py
package2/__init__.py
package2/p2.py
chankypractice-0.0.5.dist-info/LICENSE
chankypractice-0.0.5.dist-info/METADATA
chankypractice-0.0.5.dist-info/WHEEL
chankypractice-0.0.5.dist-info/top_level.txt
chankypractice-0.0.5.dist-info/RECORD
