Metadata-Version: 2.1
Name: chankypractice
Version: 0.0.5
Summary: Using find_packages()
Home-page: UNKNOWN
Author: Chanky Swami
Author-email: c.innovator@gmail.com
License: UNKNOWN
Platform: UNKNOWN
License-File: LICENSE
